zambretti_py/__init__.py
zambretti_py/zambretti.py
zambretti_py-0.0.6.dist-info/METADATA
zambretti_py-0.0.6.dist-info/WHEEL
zambretti_py-0.0.6.dist-info/licenses/LICENSE
zambretti_py-0.0.6.dist-info/RECORD
