Metadata-Version: 2.4
Name: zambretti_py
Version: 0.0.6
Summary: The Zambretti Algorithm for weather forecasting
Project-URL: Homepage, https://github.com/thestfndev/zambretti-py
Project-URL: Issues, https://github.com/thestfndev/zambretti-py/issues
Author-email: STFN <stfndev@protonmail.com>
License-File: LICENSE
Keywords: forecasting,weather,zambretti
Classifier: License :: OSI Approved :: MIT License
Classifier: Operating System :: OS Independent
Classifier: Programming Language :: Python :: 3
Requires-Python: >=3.9
